bw_timex_app/__init__.py
bw_timex_app/cli.py
bw_timex_app/welcome.py
bw_timex_app/pages/calculate.py
bw_timex_app/pages/mode.py
bw_timex_app/pages/project_selection.py
bw_timex_app/pages/temporalize.py
bw_timex_app-0.2.2.dist-info/licenses/LICENSE
bw_timex_app-0.2.2.dist-info/METADATA
bw_timex_app-0.2.2.dist-info/WHEEL
bw_timex_app-0.2.2.dist-info/entry_points.txt
bw_timex_app-0.2.2.dist-info/top_level.txt
bw_timex_app-0.2.2.dist-info/RECORD
