Metadata-Version: 2.4
Name: bw_timex_app
Version: 0.2.2
Summary: Streamlit app for bw_timex
Author-email: Timo Diepers <timo.diepers@ltt.rwth-aachen.de>
Maintainer-email: Timo Diepers <timo.diepers@ltt.rwth-aachen.de>
Project-URL: source, https://github.com/TimoDiepers/bw_timex_app
Project-URL: homepage, https://github.com/TimoDiepers/bw_timex_app
Project-URL: tracker, https://github.com/TimoDiepers/bw_timex_app/issues
Classifier: Development Status :: 4 - Beta
Classifier: Programming Language :: Python
Classifier: Programming Language :: Python :: 3
Classifier: Programming Language :: Python :: 3.9
Classifier: Programming Language :: Python :: 3.10
Classifier: Programming Language :: Python :: 3.11
Classifier: Programming Language :: Python :: 3.12
Classifier: Natural Language :: English
Classifier: Operating System :: OS Independent
Classifier: Topic :: Scientific/Engineering
Requires-Python: >=3.9
License-File: LICENSE
Requires-Dist: bw_timex>=0.3.1
Requires-Dist: streamlit>=1.38.0
Requires-Dist: plotly
Provides-Extra: testing
Requires-Dist: bw_timex_app; extra == "testing"
Requires-Dist: pytest; extra == "testing"
Requires-Dist: pytest-cov; extra == "testing"
Requires-Dist: python-coveralls; extra == "testing"
Provides-Extra: dev
Requires-Dist: build; extra == "dev"
Requires-Dist: pre-commit; extra == "dev"
Requires-Dist: pylint; extra == "dev"
Requires-Dist: pytest; extra == "dev"
Requires-Dist: pytest-cov; extra == "dev"
Requires-Dist: pytest-randomly; extra == "dev"
Requires-Dist: setuptools; extra == "dev"
Dynamic: license-file
